aio_dtls/__init__.py
aio_dtls/exceptions.py
aio_dtls/math.py
aio_dtls/protocol.py
aio_dtls/cipher/__init__.py
aio_dtls/cipher/aes_128_cbc.py
aio_dtls/cipher/aes_256_cbc.py
aio_dtls/cipher/aes_xxx_cbc.py
aio_dtls/cipher/cipher.py
aio_dtls/connection_manager/__init__.py
aio_dtls/connection_manager/cipher_suites.py
aio_dtls/connection_manager/compression_methods.py
aio_dtls/connection_manager/connection.py
aio_dtls/connection_manager/connection_manager.py
aio_dtls/connection_manager/ec_point_formats.py
aio_dtls/connection_manager/elliptic_curves.py
aio_dtls/connection_manager/enum_props.py
aio_dtls/connection_manager/signature_scheme.py
aio_dtls/connection_manager/ssl_versions.py
aio_dtls/const/__init__.py
aio_dtls/const/cipher_suites.py
aio_dtls/const/dtls.py
aio_dtls/const/handshake.py
aio_dtls/const/hashes.py
aio_dtls/const/tls.py
aio_dtls/constructs/__init__.py
aio_dtls/constructs/dtls.py
aio_dtls/constructs/helper.py
aio_dtls/constructs/old_construct.py
aio_dtls/constructs/tls.py
aio_dtls/constructs/tls_ecc.py
aio_dtls/dtls/__init__.py
aio_dtls/dtls/ecdh_anon.py
aio_dtls/dtls/handshake.py
aio_dtls/dtls/handshake_ecdh_anon.py
aio_dtls/dtls/handshake_ecdh_ecdsa.py
aio_dtls/dtls/handshake_ecdhe_psk.py
aio_dtls/dtls/helper.py
aio_dtls/dtls/protocol.py
aio_dtls/dtls/record_layer.py
aio_dtls/dtls/socket.py
aio_dtls/tls/__init__.py
aio_dtls/tls/handshake.py
aio_dtls/tls/handshake_ecdh_anon.py
aio_dtls/tls/handshake_ecdhe_ecdsa.py
aio_dtls/tls/handshake_ecdhe_psk.py
aio_dtls/tls/helper.py
aio_dtls/tls/protocol.py
aio_dtls/tls/record_layer.py
aio_dtls/tls/socket.py
aio_dtls-0.0.4.dist-info/LICENSE
aio_dtls-0.0.4.dist-info/METADATA
aio_dtls-0.0.4.dist-info/WHEEL
aio_dtls-0.0.4.dist-info/top_level.txt
aio_dtls-0.0.4.dist-info/RECORD
