Metadata-Version: 2.1
Name: aio_dtls
Version: 0.0.4
Summary: asyncio implementation of the dtls protocol in python
Home-page: https://github.com/businka/aio_dtls
Author: Razgovorov Mikhail
Author-email: 1338833@gmail.com
License: MIT
Keywords: python tls dtls mbed asyncio
Classifier: Development Status :: 2 - Pre-Alpha
Classifier: Natural Language :: Russian
Classifier: License :: OSI Approved :: MIT License
Classifier: Programming Language :: Python :: 3
Classifier: Topic :: Software Development
Classifier: Operating System :: OS Independent
Requires-Python: >=3.9
License-File: LICENSE
Requires-Dist: construct
Requires-Dist: cryptography
